LICENSE
README.md
setup.py
gmap/Hardware.py
gmap/__init__.py
gmap/compiler.py
gmap/hardware.py
gmap/mapping.py
gmap/matrix/__init__.py
gmap/matrix/generator.py
gmap/matrix/utils.py
gmap_compiler.egg-info/PKG-INFO
gmap_compiler.egg-info/SOURCES.txt
gmap_compiler.egg-info/dependency_links.txt
gmap_compiler.egg-info/requires.txt
gmap_compiler.egg-info/top_level.txt