Metadata-Version: 2.1
Name: gmap-compiler
Version: 1.1
Summary: A versatile, easy-to-use and open-source compiler that can efficiently map any arbitrary connectivity matrix to various hardware architectures.
Home-page: https://github.com/EIS-Hub/GMap
Author: Jimmy Weber
Author-email: jimmy.weber@ini.ethz.ch
License-File: LICENSE
